pydantic_variants/__init__.py
pydantic_variants/core.py
pydantic_variants/decorators.py
pydantic_variants/field_ops.py
pydantic_variants/py.typed
pydantic_variants/schema_utils.py
pydantic_variants/typing_helpers.py
pydantic_variants/transformers/__init__.py
pydantic_variants/transformers/attach_builders.py
pydantic_variants/transformers/build_variant.py
pydantic_variants/transformers/computed_to_fields.py
pydantic_variants/transformers/connect_variant.py
pydantic_variants/transformers/extract_variant.py
pydantic_variants/transformers/filter_fields.py
pydantic_variants/transformers/filter_tag.py
pydantic_variants/transformers/make_optional.py
pydantic_variants/transformers/model_dict.py
pydantic_variants/transformers/modify_fields.py
pydantic_variants/transformers/rename_fields.py
pydantic_variants/transformers/set_attributes.py
pydantic_variants/transformers/set_build_method.py
pydantic_variants/transformers/set_fields.py
pydantic_variants/transformers/switch_variant.py
pydantic_variants-0.7.1.dist-info/METADATA
pydantic_variants-0.7.1.dist-info/WHEEL
pydantic_variants-0.7.1.dist-info/licenses/LICENSE.txt
pydantic_variants-0.7.1.dist-info/RECORD
