Metadata-Version: 2.4
Name: pydantic-variants
Version: 0.7.1
Summary: Create Pydantic model variants with transformation pipelines for different use cases (Input/Output/Update)
Author-email: MikeOfZen <michael.zl.prime@gmail.com>
License: Apache-2.0
License-File: LICENSE.txt
Keywords: api,crud,dataclass,decorator,fastapi,forms,json,model,models,orm,pydantic,rest,schema,serialization,typing,validation
Classifier: Framework :: FastAPI
Classifier: Framework :: Pydantic
Classifier: Framework :: Pydantic :: 2
Classifier: Intended Audience :: Developers
Classifier: License :: OSI Approved :: Apache Software License
Classifier: Operating System :: OS Independent
Classifier: Programming Language :: Python :: 3
Classifier: Topic :: File Formats :: JSON :: JSON Schema
Classifier: Topic :: Internet :: WWW/HTTP
Classifier: Topic :: Internet :: WWW/HTTP :: HTTP Servers
Classifier: Topic :: Software Development :: Code Generators
Classifier: Topic :: Software Development :: Libraries :: Python Modules
Classifier: Topic :: Utilities
Classifier: Typing :: Typed
Requires-Python: >=3.12
Requires-Dist: pydantic>=2.11.7
